MyEaskCsv
