Metadata-Version: 1.0
Name: MyEasyCsv
Version: 0.1.5
Summary: easy csv
Home-page: UNKNOWN
Author: WJA
Author-email: 1085561450@qq.com
License: UNKNOWN
Platform: UNKNOWN
